{
  "updatedAt": "2026-07-10T06:37:05.625Z",
  "total": 251,
  "items": [
    {
      "name": "ハイビジョン",
      "slug": "ハイビジョン",
      "workCount": 2826
    },
    {
      "name": "単体作品",
      "slug": "単体作品",
      "workCount": 1913
    },
    {
      "name": "独占配信",
      "slug": "独占配信",
      "workCount": 1576
    },
    {
      "name": "中出し",
      "slug": "中出し",
      "workCount": 1422
    },
    {
      "name": "巨乳",
      "slug": "巨乳",
      "workCount": 1264
    },
    {
      "name": "4K",
      "slug": "4k",
      "workCount": 1108
    },
    {
      "name": "美少女",
      "slug": "美少女",
      "workCount": 546
    },
    {
      "name": "人妻・主婦",
      "slug": "人妻・主婦",
      "workCount": 537
    },
    {
      "name": "フェラ",
      "slug": "フェラ",
      "workCount": 455
    },
    {
      "name": "痴女",
      "slug": "痴女",
      "workCount": 350
    },
    {
      "name": "寝取り・寝取られ・NTR",
      "slug": "寝取り・寝取られ・ntr",
      "workCount": 343
    },
    {
      "name": "4時間以上作品",
      "slug": "4時間以上作品",
      "workCount": 336
    },
    {
      "name": "熟女",
      "slug": "熟女",
      "workCount": 334
    },
    {
      "name": "素人",
      "slug": "素人",
      "workCount": 297
    },
    {
      "name": "3P・4P",
      "slug": "3p・4p",
      "workCount": 292
    },
    {
      "name": "淫乱・ハード系",
      "slug": "淫乱・ハード系",
      "workCount": 286
    },
    {
      "name": "パイズリ",
      "slug": "パイズリ",
      "workCount": 279
    },
    {
      "name": "スレンダー",
      "slug": "スレンダー",
      "workCount": 278
    },
    {
      "name": "潮吹き",
      "slug": "潮吹き",
      "workCount": 275
    },
    {
      "name": "妄想族",
      "slug": "妄想族",
      "workCount": 272
    },
    {
      "name": "アクメ・オーガズム",
      "slug": "アクメ・オーガズム",
      "workCount": 232
    },
    {
      "name": "騎乗位",
      "slug": "騎乗位",
      "workCount": 201
    },
    {
      "name": "ハメ撮り",
      "slug": "ハメ撮り",
      "workCount": 191
    },
    {
      "name": "女子校生",
      "slug": "女子校生",
      "workCount": 177
    },
    {
      "name": "ドラマ",
      "slug": "ドラマ",
      "workCount": 171
    },
    {
      "name": "キス・接吻",
      "slug": "キス・接吻",
      "workCount": 165
    },
    {
      "name": "美乳",
      "slug": "美乳",
      "workCount": 164
    },
    {
      "name": "顔射",
      "slug": "顔射",
      "workCount": 151
    },
    {
      "name": "巨尻",
      "slug": "巨尻",
      "workCount": 141
    },
    {
      "name": "不倫",
      "slug": "不倫",
      "workCount": 134
    },
    {
      "name": "ベスト・総集編",
      "slug": "ベスト・総集編",
      "workCount": 125
    },
    {
      "name": "OL",
      "slug": "ol",
      "workCount": 122
    },
    {
      "name": "乱交",
      "slug": "乱交",
      "workCount": 118
    },
    {
      "name": "制服",
      "slug": "制服",
      "workCount": 117
    },
    {
      "name": "イラマチオ",
      "slug": "イラマチオ",
      "workCount": 110
    },
    {
      "name": "お姉さん",
      "slug": "お姉さん",
      "workCount": 110
    },
    {
      "name": "デビュー作品",
      "slug": "デビュー作品",
      "workCount": 107
    },
    {
      "name": "ドキュメンタリー",
      "slug": "ドキュメンタリー",
      "workCount": 102
    },
    {
      "name": "辱め",
      "slug": "辱め",
      "workCount": 102
    },
    {
      "name": "コスプレ",
      "slug": "コスプレ",
      "workCount": 97
    },
    {
      "name": "デジモ",
      "slug": "デジモ",
      "workCount": 93
    },
    {
      "name": "羞恥",
      "slug": "羞恥",
      "workCount": 87
    },
    {
      "name": "オナニー",
      "slug": "オナニー",
      "workCount": 85
    },
    {
      "name": "尻フェチ",
      "slug": "尻フェチ",
      "workCount": 85
    },
    {
      "name": "手コキ",
      "slug": "手コキ",
      "workCount": 82
    },
    {
      "name": "ローション・オイル",
      "slug": "ローション・オイル",
      "workCount": 81
    },
    {
      "name": "女子大生",
      "slug": "女子大生",
      "workCount": 81
    },
    {
      "name": "ギャル",
      "slug": "ギャル",
      "workCount": 77
    },
    {
      "name": "その他フェチ",
      "slug": "その他フェチ",
      "workCount": 73
    },
    {
      "name": "巨乳フェチ",
      "slug": "巨乳フェチ",
      "workCount": 73
    },
    {
      "name": "エステ",
      "slug": "エステ",
      "workCount": 72
    },
    {
      "name": "アイドル・芸能人",
      "slug": "アイドル・芸能人",
      "workCount": 68
    },
    {
      "name": "盗撮・のぞき",
      "slug": "盗撮・のぞき",
      "workCount": 67
    },
    {
      "name": "女優ベスト・総集編",
      "slug": "女優ベスト・総集編",
      "workCount": 66
    },
    {
      "name": "パイパン",
      "slug": "パイパン",
      "workCount": 64
    },
    {
      "name": "ごっくん",
      "slug": "ごっくん",
      "workCount": 63
    },
    {
      "name": "マッサージ・リフレ",
      "slug": "マッサージ・リフレ",
      "workCount": 63
    },
    {
      "name": "汗だく",
      "slug": "汗だく",
      "workCount": 63
    },
    {
      "name": "M女",
      "slug": "m女",
      "workCount": 62
    },
    {
      "name": "ナンパ",
      "slug": "ナンパ",
      "workCount": 62
    },
    {
      "name": "主観",
      "slug": "主観",
      "workCount": 61
    },
    {
      "name": "鬼畜",
      "slug": "鬼畜",
      "workCount": 60
    },
    {
      "name": "拘束",
      "slug": "拘束",
      "workCount": 59
    },
    {
      "name": "姉・妹",
      "slug": "姉・妹",
      "workCount": 59
    },
    {
      "name": "職業色々",
      "slug": "職業色",
      "workCount": 57
    },
    {
      "name": "近親相姦",
      "slug": "近親相姦",
      "workCount": 56
    },
    {
      "name": "淫語",
      "slug": "淫語",
      "workCount": 55
    },
    {
      "name": "企画",
      "slug": "企画",
      "workCount": 53
    },
    {
      "name": "デカチン・巨根",
      "slug": "デカチン・巨根",
      "workCount": 52
    },
    {
      "name": "ぶっかけ",
      "slug": "ぶっかけ",
      "workCount": 52
    },
    {
      "name": "温泉",
      "slug": "温泉",
      "workCount": 49
    },
    {
      "name": "バック",
      "slug": "バック",
      "workCount": 48
    },
    {
      "name": "放尿・お漏らし",
      "slug": "放尿・お漏らし",
      "workCount": 48
    },
    {
      "name": "ハーレム",
      "slug": "ハーレム",
      "workCount": 47
    },
    {
      "name": "16時間以上作品",
      "slug": "16時間以上作品",
      "workCount": 46
    },
    {
      "name": "縛り・緊縛",
      "slug": "縛り・緊縛",
      "workCount": 45
    },
    {
      "name": "M男",
      "slug": "m男",
      "workCount": 44
    },
    {
      "name": "アナル",
      "slug": "アナル",
      "workCount": 43
    },
    {
      "name": "ミニ系",
      "slug": "ミニ系",
      "workCount": 43
    },
    {
      "name": "ギリモザ",
      "slug": "ギリモザ",
      "workCount": 42
    },
    {
      "name": "野外・露出",
      "slug": "野外・露出",
      "workCount": 41
    },
    {
      "name": "キャバ嬢・風俗嬢",
      "slug": "キャバ嬢・風俗嬢",
      "workCount": 40
    },
    {
      "name": "小柄",
      "slug": "小柄",
      "workCount": 40
    },
    {
      "name": "おもちゃ",
      "slug": "おもちゃ",
      "workCount": 39
    },
    {
      "name": "レズビアン",
      "slug": "レズビアン",
      "workCount": 38
    },
    {
      "name": "競泳・スクール水着",
      "slug": "競泳・スクール水着",
      "workCount": 38
    },
    {
      "name": "パンスト・タイツ",
      "slug": "パンスト・タイツ",
      "workCount": 37
    },
    {
      "name": "原作コラボ",
      "slug": "原作コラボ",
      "workCount": 37
    },
    {
      "name": "超乳",
      "slug": "超乳",
      "workCount": 36
    },
    {
      "name": "童貞",
      "slug": "童貞",
      "workCount": 36
    },
    {
      "name": "女教師",
      "slug": "女教師",
      "workCount": 35
    },
    {
      "name": "貧乳・微乳",
      "slug": "貧乳・微乳",
      "workCount": 35
    },
    {
      "name": "ぽっちゃり",
      "slug": "ぽっちゃり",
      "workCount": 34
    },
    {
      "name": "SM",
      "slug": "sm",
      "workCount": 33
    },
    {
      "name": "看護婦・ナース",
      "slug": "看護婦・ナース",
      "workCount": 33
    },
    {
      "name": "水着",
      "slug": "水着",
      "workCount": 33
    },
    {
      "name": "アクション・格闘",
      "slug": "アクション・格闘",
      "workCount": 31
    },
    {
      "name": "女装・男の娘",
      "slug": "女装・男の娘",
      "workCount": 31
    },
    {
      "name": "ニューハーフ",
      "slug": "ニューハーフ",
      "workCount": 30
    },
    {
      "name": "学生服",
      "slug": "学生服",
      "workCount": 30
    },
    {
      "name": "即ハメ",
      "slug": "即ハメ",
      "workCount": 30
    },
    {
      "name": "長身",
      "slug": "長身",
      "workCount": 30
    },
    {
      "name": "ヘルス・ソープ",
      "slug": "ヘルス・ソープ",
      "workCount": 29
    },
    {
      "name": "アナルセックス（男の娘）",
      "slug": "アナルセックス-男の娘",
      "workCount": 27
    },
    {
      "name": "お風呂",
      "slug": "お風呂",
      "workCount": 27
    },
    {
      "name": "お母さん",
      "slug": "お母さん",
      "workCount": 27
    },
    {
      "name": "クンニ",
      "slug": "クンニ",
      "workCount": 27
    },
    {
      "name": "ドラッグ",
      "slug": "ドラッグ",
      "workCount": 26
    },
    {
      "name": "イメージビデオ",
      "slug": "イメージビデオ",
      "workCount": 25
    },
    {
      "name": "パンチラ",
      "slug": "パンチラ",
      "workCount": 25
    },
    {
      "name": "めがね",
      "slug": "めがね",
      "workCount": 25
    },
    {
      "name": "女上司",
      "slug": "女上司",
      "workCount": 25
    },
    {
      "name": "孕ませ",
      "slug": "孕ませ",
      "workCount": 25
    },
    {
      "name": "部下・同僚",
      "slug": "部下・同僚",
      "workCount": 24
    },
    {
      "name": "恋愛",
      "slug": "恋愛",
      "workCount": 23
    },
    {
      "name": "アナルセックス",
      "slug": "アナルセックス",
      "workCount": 22
    },
    {
      "name": "セクシー",
      "slug": "セクシー",
      "workCount": 22
    },
    {
      "name": "ファン感謝・訪問",
      "slug": "ファン感謝・訪問",
      "workCount": 22
    },
    {
      "name": "ランジェリー",
      "slug": "ランジェリー",
      "workCount": 22
    },
    {
      "name": "レズキス",
      "slug": "レズキス",
      "workCount": 22
    },
    {
      "name": "エマニエル",
      "slug": "エマニエル",
      "workCount": 21
    },
    {
      "name": "バイブ",
      "slug": "バイブ",
      "workCount": 21
    },
    {
      "name": "メイド",
      "slug": "メイド",
      "workCount": 21
    },
    {
      "name": "脚フェチ",
      "slug": "脚フェチ",
      "workCount": 21
    },
    {
      "name": "局部アップ",
      "slug": "局部アップ",
      "workCount": 21
    },
    {
      "name": "オナサポ",
      "slug": "オナサポ",
      "workCount": 20
    },
    {
      "name": "スポーツ",
      "slug": "スポーツ",
      "workCount": 19
    },
    {
      "name": "ビッチ",
      "slug": "ビッチ",
      "workCount": 19
    },
    {
      "name": "白人女優",
      "slug": "白人女優",
      "workCount": 19
    },
    {
      "name": "セーラー服",
      "slug": "セーラー服",
      "workCount": 18
    },
    {
      "name": "ホテル",
      "slug": "ホテル",
      "workCount": 18
    },
    {
      "name": "顔面騎乗",
      "slug": "顔面騎乗",
      "workCount": 18
    },
    {
      "name": "体操着・ブルマ",
      "slug": "体操着・ブルマ",
      "workCount": 18
    },
    {
      "name": "監禁",
      "slug": "監禁",
      "workCount": 17
    },
    {
      "name": "和服・浴衣",
      "slug": "和服・浴衣",
      "workCount": 17
    },
    {
      "name": "イタズラ",
      "slug": "イタズラ",
      "workCount": 16
    },
    {
      "name": "デート",
      "slug": "デート",
      "workCount": 16
    },
    {
      "name": "義母",
      "slug": "義母",
      "workCount": 16
    },
    {
      "name": "若妻・幼妻",
      "slug": "若妻・幼妻",
      "workCount": 16
    },
    {
      "name": "旅行",
      "slug": "旅行",
      "workCount": 16
    },
    {
      "name": "アスリート",
      "slug": "アスリート",
      "workCount": 15
    },
    {
      "name": "電マ",
      "slug": "電マ",
      "workCount": 15
    },
    {
      "name": "白目・失神",
      "slug": "白目・失神",
      "workCount": 15
    },
    {
      "name": "指マン",
      "slug": "指マン",
      "workCount": 14
    },
    {
      "name": "男の潮吹き",
      "slug": "男の潮吹き",
      "workCount": 14
    },
    {
      "name": "着エロ",
      "slug": "着エロ",
      "workCount": 13
    },
    {
      "name": "カップル",
      "slug": "カップル",
      "workCount": 12
    },
    {
      "name": "ビジネススーツ",
      "slug": "ビジネススーツ",
      "workCount": 12
    },
    {
      "name": "秘書",
      "slug": "秘書",
      "workCount": 12
    },
    {
      "name": "AI生成作品",
      "slug": "ai生成作品",
      "workCount": 11
    },
    {
      "name": "逆ナン",
      "slug": "逆ナン",
      "workCount": 11
    },
    {
      "name": "女捜査官",
      "slug": "女捜査官",
      "workCount": 11
    },
    {
      "name": "部活・マネージャー",
      "slug": "部活・マネージャー",
      "workCount": 11
    },
    {
      "name": "浣腸",
      "slug": "浣腸",
      "workCount": 11
    },
    {
      "name": "クラシック",
      "slug": "クラシック",
      "workCount": 10
    },
    {
      "name": "シックスナイン",
      "slug": "シックスナイン",
      "workCount": 10
    },
    {
      "name": "ノーブラ",
      "slug": "ノーブラ",
      "workCount": 10
    },
    {
      "name": "学園もの",
      "slug": "学園もの",
      "workCount": 10
    },
    {
      "name": "足コキ",
      "slug": "足コキ",
      "workCount": 10
    },
    {
      "name": "日焼け",
      "slug": "日焼け",
      "workCount": 10
    },
    {
      "name": "病院・クリニック",
      "slug": "病院・クリニック",
      "workCount": 10
    },
    {
      "name": "幼なじみ",
      "slug": "幼なじみ",
      "workCount": 10
    },
    {
      "name": "異物挿入",
      "slug": "異物挿入",
      "workCount": 9
    },
    {
      "name": "How To",
      "slug": "how-to",
      "workCount": 8
    },
    {
      "name": "バニーガール",
      "slug": "バニーガール",
      "workCount": 8
    },
    {
      "name": "拷問",
      "slug": "拷問",
      "workCount": 8
    },
    {
      "name": "叔母さん",
      "slug": "叔母さん",
      "workCount": 8
    },
    {
      "name": "裸エプロン",
      "slug": "裸エプロン",
      "workCount": 8
    },
    {
      "name": "カーセックス",
      "slug": "カーセックス",
      "workCount": 7
    },
    {
      "name": "スパンキング",
      "slug": "スパンキング",
      "workCount": 7
    },
    {
      "name": "セット商品",
      "slug": "セット商品",
      "workCount": 7
    },
    {
      "name": "ミニスカ",
      "slug": "ミニスカ",
      "workCount": 7
    },
    {
      "name": "飲み会・合コン",
      "slug": "飲み会・合コン",
      "workCount": 7
    },
    {
      "name": "時間停止",
      "slug": "時間停止",
      "workCount": 7
    },
    {
      "name": "インストラクター",
      "slug": "インストラクター",
      "workCount": 6
    },
    {
      "name": "ファンタジー",
      "slug": "ファンタジー",
      "workCount": 6
    },
    {
      "name": "女性向け",
      "slug": "女性向け",
      "workCount": 6
    },
    {
      "name": "投稿",
      "slug": "投稿",
      "workCount": 6
    },
    {
      "name": "洋ピン・海外輸入",
      "slug": "洋ピン・海外輸入",
      "workCount": 6
    },
    {
      "name": "スチュワーデス",
      "slug": "スチュワーデス",
      "workCount": 5
    },
    {
      "name": "ディルド",
      "slug": "ディルド",
      "workCount": 5
    },
    {
      "name": "ローター",
      "slug": "ローター",
      "workCount": 5
    },
    {
      "name": "家庭教師",
      "slug": "家庭教師",
      "workCount": 5
    },
    {
      "name": "黒人男優",
      "slug": "黒人男優",
      "workCount": 5
    },
    {
      "name": "女医",
      "slug": "女医",
      "workCount": 5
    },
    {
      "name": "女子アナ",
      "slug": "女子アナ",
      "workCount": 5
    },
    {
      "name": "早漏",
      "slug": "早漏",
      "workCount": 5
    },
    {
      "name": "軟体",
      "slug": "軟体",
      "workCount": 5
    },
    {
      "name": "複数話",
      "slug": "複数話",
      "workCount": 5
    },
    {
      "name": "娘・養女",
      "slug": "娘・養女",
      "workCount": 5
    },
    {
      "name": "面接",
      "slug": "面接",
      "workCount": 5
    },
    {
      "name": "オタク",
      "slug": "オタク",
      "workCount": 4
    },
    {
      "name": "お爺ちゃん",
      "slug": "お爺ちゃん",
      "workCount": 4
    },
    {
      "name": "飲尿",
      "slug": "飲尿",
      "workCount": 4
    },
    {
      "name": "女王様",
      "slug": "女王様",
      "workCount": 4
    },
    {
      "name": "体験告白",
      "slug": "体験告白",
      "workCount": 4
    },
    {
      "name": "鼻フック",
      "slug": "鼻フック",
      "workCount": 4
    },
    {
      "name": "未亡人",
      "slug": "未亡人",
      "workCount": 4
    },
    {
      "name": "アジア女優",
      "slug": "アジア女優",
      "workCount": 3
    },
    {
      "name": "お嬢様・令嬢",
      "slug": "お嬢様・令嬢",
      "workCount": 3
    },
    {
      "name": "クスコ",
      "slug": "クスコ",
      "workCount": 3
    },
    {
      "name": "ゲロ",
      "slug": "ゲロ",
      "workCount": 3
    },
    {
      "name": "スワッピング・夫婦交換",
      "slug": "スワッピング・夫婦交換",
      "workCount": 3
    },
    {
      "name": "ダンス",
      "slug": "ダンス",
      "workCount": 3
    },
    {
      "name": "チャイナドレス",
      "slug": "チャイナドレス",
      "workCount": 3
    },
    {
      "name": "ポルチオ",
      "slug": "ポルチオ",
      "workCount": 3
    },
    {
      "name": "ボンテージ",
      "slug": "ボンテージ",
      "workCount": 3
    },
    {
      "name": "ママ友",
      "slug": "ママ友",
      "workCount": 3
    },
    {
      "name": "モデル",
      "slug": "モデル",
      "workCount": 3
    },
    {
      "name": "レースクィーン",
      "slug": "レースクィーン",
      "workCount": 3
    },
    {
      "name": "レオタード",
      "slug": "レオタード",
      "workCount": 3
    },
    {
      "name": "胸チラ",
      "slug": "胸チラ",
      "workCount": 3
    },
    {
      "name": "処女",
      "slug": "処女",
      "workCount": 3
    },
    {
      "name": "復刻",
      "slug": "復刻",
      "workCount": 3
    },
    {
      "name": "変身ヒロイン",
      "slug": "変身ヒロイン",
      "workCount": 3
    },
    {
      "name": "母乳",
      "slug": "母乳",
      "workCount": 3
    },
    {
      "name": "ウェイトレス",
      "slug": "ウェイトレス",
      "workCount": 2
    },
    {
      "name": "スカトロ",
      "slug": "スカトロ",
      "workCount": 2
    },
    {
      "name": "チアガール",
      "slug": "チアガール",
      "workCount": 2
    },
    {
      "name": "ツンデレ",
      "slug": "ツンデレ",
      "workCount": 2
    },
    {
      "name": "ニーソックス",
      "slug": "ニーソックス",
      "workCount": 2
    },
    {
      "name": "ルーズソックス",
      "slug": "ルーズソックス",
      "workCount": 2
    },
    {
      "name": "筋肉",
      "slug": "筋肉",
      "workCount": 2
    },
    {
      "name": "脱糞",
      "slug": "脱糞",
      "workCount": 2
    },
    {
      "name": "福袋",
      "slug": "福袋",
      "workCount": 2
    },
    {
      "name": "覆面・マスク",
      "slug": "覆面・マスク",
      "workCount": 2
    },
    {
      "name": "妄想",
      "slug": "妄想",
      "workCount": 2
    },
    {
      "name": "3D",
      "slug": "3d",
      "workCount": 1
    },
    {
      "name": "FANZA配信限定",
      "slug": "fanza配信限定",
      "workCount": 1
    },
    {
      "name": "SF",
      "slug": "sf",
      "workCount": 1
    },
    {
      "name": "お婆ちゃん",
      "slug": "お婆ちゃん",
      "workCount": 1
    },
    {
      "name": "ギャグ・コメディ",
      "slug": "ギャグ・コメディ",
      "workCount": 1
    },
    {
      "name": "くすぐり",
      "slug": "くすぐり",
      "workCount": 1
    },
    {
      "name": "ショタ",
      "slug": "ショタ",
      "workCount": 1
    },
    {
      "name": "スマホ推奨縦動画",
      "slug": "スマホ推奨縦動画",
      "workCount": 1
    },
    {
      "name": "セレブ",
      "slug": "セレブ",
      "workCount": 1
    },
    {
      "name": "ダーク系",
      "slug": "ダーク系",
      "workCount": 1
    },
    {
      "name": "ネコミミ・獣系",
      "slug": "ネコミミ・獣系",
      "workCount": 1
    },
    {
      "name": "ボディコン",
      "slug": "ボディコン",
      "workCount": 1
    },
    {
      "name": "ヨガ",
      "slug": "ヨガ",
      "workCount": 1
    },
    {
      "name": "花嫁",
      "slug": "花嫁",
      "workCount": 1
    },
    {
      "name": "格闘家",
      "slug": "格闘家",
      "workCount": 1
    },
    {
      "name": "受付嬢",
      "slug": "受付嬢",
      "workCount": 1
    },
    {
      "name": "性転換・女体化",
      "slug": "性転換・女体化",
      "workCount": 1
    },
    {
      "name": "台湾モデル",
      "slug": "台湾モデル",
      "workCount": 1
    },
    {
      "name": "妊婦",
      "slug": "妊婦",
      "workCount": 1
    },
    {
      "name": "罵倒",
      "slug": "罵倒",
      "workCount": 1
    },
    {
      "name": "妄想族2021年上半期ヒットTOP100",
      "slug": "妄想族2021年上半期ヒットtop100",
      "workCount": 1
    },
    {
      "name": "妄想族2022年下半期ヒットTOP100",
      "slug": "妄想族2022年下半期ヒットtop100",
      "workCount": 1
    },
    {
      "name": "蝋燭",
      "slug": "蝋燭",
      "workCount": 1
    },
    {
      "name": "巫女",
      "slug": "巫女",
      "workCount": 1
    }
  ]
}
