{
  "processId": "batch-1783740689111-varnen",
  "phase": "collecting",
  "targetTotalCount": 10000,
  "startOffset": 1101,
  "requestCount": 500,
  "addLimit": 500,
  "maxBatches": 1,
  "batchesExecuted": 0,
  "currentCatalogCount": 6450,
  "works": [],
  "runStats": null,
  "progressMessage": "人気順から候補を取得中...",
  "validatingProgress": 0,
  "validatingTotal": 0,
  "createdAt": "2026-07-11T03:31:30.379Z",
  "updatedAt": "2026-07-11T03:31:30.379Z",
  "completedAt": null,
  "errorCode": null,
  "startSha": "669d4c2b43478c02ad5fcebd49e965304b3eaf77",
  "saveSha": null,
  "retryCount": 0,
  "durationMs": null
}
