{
  "updatedAt": "2026-07-10T23:23:15.265Z",
  "total": 376,
  "items": [
    {
      "name": "1113工房/妄想族",
      "slug": "1113工房-妄想族",
      "workCount": 1
    },
    {
      "name": "ABC/妄想族",
      "slug": "abc-妄想族",
      "workCount": 19
    },
    {
      "name": "AGA",
      "slug": "aga",
      "workCount": 4
    },
    {
      "name": "Aircontrol",
      "slug": "aircontrol",
      "workCount": 3
    },
    {
      "name": "ANI＋I",
      "slug": "ani-i",
      "workCount": 2
    },
    {
      "name": "Asia/妄想族",
      "slug": "asia-妄想族",
      "workCount": 1
    },
    {
      "name": "ASSMI",
      "slug": "assmi",
      "workCount": 1
    },
    {
      "name": "ATOM",
      "slug": "atom",
      "workCount": 8
    },
    {
      "name": "AVS collector’s",
      "slug": "avs-collector-s",
      "workCount": 68
    },
    {
      "name": "BabyEntertainment",
      "slug": "babyentertainment",
      "workCount": 2
    },
    {
      "name": "BALTAN＜バルタン＞",
      "slug": "baltan-バルタン",
      "workCount": 5
    },
    {
      "name": "BAZOOKA",
      "slug": "bazooka",
      "workCount": 19
    },
    {
      "name": "BEATLE",
      "slug": "beatle",
      "workCount": 2
    },
    {
      "name": "BeFree",
      "slug": "befree",
      "workCount": 7
    },
    {
      "name": "BonキュンBon",
      "slug": "bonキュンbon",
      "workCount": 1
    },
    {
      "name": "BOTAN",
      "slug": "botan",
      "workCount": 2
    },
    {
      "name": "BRILL（JADE）",
      "slug": "brill-jade",
      "workCount": 24
    },
    {
      "name": "Brolle",
      "slug": "brolle",
      "workCount": 1
    },
    {
      "name": "buffet",
      "slug": "buffet",
      "workCount": 1
    },
    {
      "name": "CHCスタジオ",
      "slug": "chcスタジオ",
      "workCount": 1
    },
    {
      "name": "CHoBitcH",
      "slug": "chobitch",
      "workCount": 2
    },
    {
      "name": "ChuChuGirl（チュチュガール）",
      "slug": "chuchugirl-チュチュガール",
      "workCount": 1
    },
    {
      "name": "CUBE",
      "slug": "cube",
      "workCount": 2
    },
    {
      "name": "DAHLIA",
      "slug": "dahlia",
      "workCount": 29
    },
    {
      "name": "DANDY",
      "slug": "dandy",
      "workCount": 10
    },
    {
      "name": "deep/妄想族",
      "slug": "deep-妄想族",
      "workCount": 2
    },
    {
      "name": "DOC",
      "slug": "doc",
      "workCount": 86
    },
    {
      "name": "E-BODY",
      "slug": "e-body",
      "workCount": 66
    },
    {
      "name": "EROTICA",
      "slug": "erotica",
      "workCount": 2
    },
    {
      "name": "FAIR＆WAY",
      "slug": "fair-way",
      "workCount": 12
    },
    {
      "name": "FALENO",
      "slug": "faleno",
      "workCount": 32
    },
    {
      "name": "FALENO TUBE",
      "slug": "faleno-tube",
      "workCount": 13
    },
    {
      "name": "FAプロ",
      "slug": "faプロ",
      "workCount": 10
    },
    {
      "name": "First Star",
      "slug": "first-star",
      "workCount": 39
    },
    {
      "name": "Fitch",
      "slug": "fitch",
      "workCount": 80
    },
    {
      "name": "FLAVORY（フレーバリー）",
      "slug": "flavory-フレーバリー",
      "workCount": 4
    },
    {
      "name": "Flower",
      "slug": "flower",
      "workCount": 10
    },
    {
      "name": "FunCity/妄想族",
      "slug": "funcity-妄想族",
      "workCount": 49
    },
    {
      "name": "GIGA",
      "slug": "giga",
      "workCount": 4
    },
    {
      "name": "GOS",
      "slug": "gos",
      "workCount": 1
    },
    {
      "name": "grace",
      "slug": "grace",
      "workCount": 2
    },
    {
      "name": "h.m.p",
      "slug": "h-m-p",
      "workCount": 15
    },
    {
      "name": "h.m.p DORAMA",
      "slug": "h-m-p-dorama",
      "workCount": 1
    },
    {
      "name": "HALENTINO/妄想族",
      "slug": "halentino-妄想族",
      "workCount": 8
    },
    {
      "name": "Hime.STYLE",
      "slug": "hime-style",
      "workCount": 1
    },
    {
      "name": "HMN WORKS",
      "slug": "hmn-works",
      "workCount": 30
    },
    {
      "name": "HMNダイナマイト！！/妄想族",
      "slug": "hmnダイナマイト-妄想族",
      "workCount": 2
    },
    {
      "name": "Hsoda",
      "slug": "hsoda",
      "workCount": 15
    },
    {
      "name": "Hunter",
      "slug": "hunter",
      "workCount": 74
    },
    {
      "name": "I.B.WORKS",
      "slug": "i-b-works",
      "workCount": 2
    },
    {
      "name": "INITIUM",
      "slug": "initium",
      "workCount": 20
    },
    {
      "name": "JET映像",
      "slug": "jet映像",
      "workCount": 11
    },
    {
      "name": "JUKUJO99",
      "slug": "jukujo99",
      "workCount": 17
    },
    {
      "name": "kawaii",
      "slug": "kawaii",
      "workCount": 83
    },
    {
      "name": "kira☆kira",
      "slug": "kira-kira",
      "workCount": 17
    },
    {
      "name": "KNIP",
      "slug": "knip",
      "workCount": 2
    },
    {
      "name": "KSB企画/エマニエル",
      "slug": "ksb企画-エマニエル",
      "workCount": 9
    },
    {
      "name": "KUKI",
      "slug": "kuki",
      "workCount": 8
    },
    {
      "name": "LEO",
      "slug": "leo",
      "workCount": 5
    },
    {
      "name": "LOVEま○こ/妄想族",
      "slug": "loveま-こ-妄想族",
      "workCount": 2
    },
    {
      "name": "MAGNOLIA",
      "slug": "magnolia",
      "workCount": 4
    },
    {
      "name": "MANIAQ/妄想族",
      "slug": "maniaq-妄想族",
      "workCount": 3
    },
    {
      "name": "MARLO MEDIA",
      "slug": "marlo-media",
      "workCount": 3
    },
    {
      "name": "MARRION",
      "slug": "marrion",
      "workCount": 7
    },
    {
      "name": "MBM",
      "slug": "mbm",
      "workCount": 14
    },
    {
      "name": "MDMA",
      "slug": "mdma",
      "workCount": 2
    },
    {
      "name": "MEGAMI",
      "slug": "megami",
      "workCount": 4
    },
    {
      "name": "Mellow Moon（メロウムーン）",
      "slug": "mellow-moon-メロウムーン",
      "workCount": 1
    },
    {
      "name": "MERA",
      "slug": "mera",
      "workCount": 1
    },
    {
      "name": "MERCURY（マーキュリー）",
      "slug": "mercury-マーキュリー",
      "workCount": 21
    },
    {
      "name": "MILK",
      "slug": "milk",
      "workCount": 2
    },
    {
      "name": "million",
      "slug": "million",
      "workCount": 21
    },
    {
      "name": "MONSTERS",
      "slug": "monsters",
      "workCount": 1
    },
    {
      "name": "Mr.michiru",
      "slug": "mr-michiru",
      "workCount": 12
    },
    {
      "name": "MUTEKI",
      "slug": "muteki",
      "workCount": 2
    },
    {
      "name": "M男パラダイス",
      "slug": "m男パラダイス",
      "workCount": 5
    },
    {
      "name": "NANA",
      "slug": "nana",
      "workCount": 2
    },
    {
      "name": "NIRVANA",
      "slug": "nirvana",
      "workCount": 6
    },
    {
      "name": "NON",
      "slug": "non",
      "workCount": 1
    },
    {
      "name": "NPJ",
      "slug": "npj",
      "workCount": 25
    },
    {
      "name": "OFFICE K’S",
      "slug": "office-k-s",
      "workCount": 13
    },
    {
      "name": "OPPAI",
      "slug": "oppai",
      "workCount": 52
    },
    {
      "name": "PETSHOP/妄想族",
      "slug": "petshop-妄想族",
      "workCount": 1
    },
    {
      "name": "REbecca",
      "slug": "rebecca",
      "workCount": 12
    },
    {
      "name": "ROCKET",
      "slug": "rocket",
      "workCount": 14
    },
    {
      "name": "ROOKIE",
      "slug": "rookie",
      "workCount": 25
    },
    {
      "name": "Royal Asian/妄想族",
      "slug": "royal-asian-妄想族",
      "workCount": 1
    },
    {
      "name": "S-Cute",
      "slug": "s-cute",
      "workCount": 181
    },
    {
      "name": "SEX Agent/妄想族",
      "slug": "sex-agent-妄想族",
      "workCount": 3
    },
    {
      "name": "SEX MACHINE",
      "slug": "sex-machine",
      "workCount": 6
    },
    {
      "name": "SHIGEKI",
      "slug": "shigeki",
      "workCount": 13
    },
    {
      "name": "SILK LABO",
      "slug": "silk-labo",
      "workCount": 3
    },
    {
      "name": "SILVER BIRCH",
      "slug": "silver-birch",
      "workCount": 68
    },
    {
      "name": "SODクリエイト",
      "slug": "sodクリエイト",
      "workCount": 152
    },
    {
      "name": "SUN",
      "slug": "sun",
      "workCount": 7
    },
    {
      "name": "SWITCH",
      "slug": "switch",
      "workCount": 7
    },
    {
      "name": "S級素人",
      "slug": "s級素人",
      "workCount": 3
    },
    {
      "name": "TAG/ゴールド",
      "slug": "tag-ゴールド",
      "workCount": 2
    },
    {
      "name": "TAMEIKE",
      "slug": "tameike",
      "workCount": 35
    },
    {
      "name": "TEPPAN",
      "slug": "teppan",
      "workCount": 4
    },
    {
      "name": "TICKLE PRODUCTION THRILL",
      "slug": "tickle-production-thrill",
      "workCount": 4
    },
    {
      "name": "TMA",
      "slug": "tma",
      "workCount": 8
    },
    {
      "name": "TRANS CLUB",
      "slug": "trans-club",
      "workCount": 3
    },
    {
      "name": "U-ra",
      "slug": "u-ra",
      "workCount": 1
    },
    {
      "name": "U＆K",
      "slug": "u-k",
      "workCount": 4
    },
    {
      "name": "unfinished",
      "slug": "unfinished",
      "workCount": 5
    },
    {
      "name": "V＆R PRODUCE",
      "slug": "v-r-produce",
      "workCount": 5
    },
    {
      "name": "V＆Rプランニング",
      "slug": "v-rプランニング",
      "workCount": 2
    },
    {
      "name": "VENUS",
      "slug": "venus",
      "workCount": 34
    },
    {
      "name": "VERONICA",
      "slug": "veronica",
      "workCount": 4
    },
    {
      "name": "VIP",
      "slug": "vip",
      "workCount": 14
    },
    {
      "name": "Vitamin/妄想族",
      "slug": "vitamin-妄想族",
      "workCount": 1
    },
    {
      "name": "Yellow Moon（イエロームーン）",
      "slug": "yellow-moon-イエロームーン",
      "workCount": 2
    },
    {
      "name": "YONAKA",
      "slug": "yonaka",
      "workCount": 3
    },
    {
      "name": "ZOOO",
      "slug": "zooo",
      "workCount": 11
    },
    {
      "name": "あああ",
      "slug": "あああ",
      "workCount": 1
    },
    {
      "name": "アイエナRISING",
      "slug": "アイエナrising",
      "workCount": 7
    },
    {
      "name": "アイエナジー",
      "slug": "アイエナジー",
      "workCount": 9
    },
    {
      "name": "あいすまん",
      "slug": "あいすまん",
      "workCount": 22
    },
    {
      "name": "アイデアポケット",
      "slug": "アイデアポケット",
      "workCount": 154
    },
    {
      "name": "アキノリ",
      "slug": "アキノリ",
      "workCount": 1
    },
    {
      "name": "あたご屋/エマニエル",
      "slug": "あたご屋-エマニエル",
      "workCount": 1
    },
    {
      "name": "アタッカーズ",
      "slug": "アタッカーズ",
      "workCount": 118
    },
    {
      "name": "アパッチ",
      "slug": "アパッチ",
      "workCount": 3
    },
    {
      "name": "アマTV",
      "slug": "アマtv",
      "workCount": 23
    },
    {
      "name": "アリーナエンターテインメント",
      "slug": "アリーナエンターテインメント",
      "workCount": 3
    },
    {
      "name": "アリスJAPAN",
      "slug": "アリスjapan",
      "workCount": 161
    },
    {
      "name": "アロマ企画",
      "slug": "アロマ企画",
      "workCount": 15
    },
    {
      "name": "アングラ本舗",
      "slug": "アングラ本舗",
      "workCount": 2
    },
    {
      "name": "あんでるへん",
      "slug": "あんでるへん",
      "workCount": 3
    },
    {
      "name": "いきなりエロざんまい",
      "slug": "いきなりエロざんまい",
      "workCount": 59
    },
    {
      "name": "うさぎ/妄想族",
      "slug": "うさぎ-妄想族",
      "workCount": 8
    },
    {
      "name": "うらキン",
      "slug": "うらキン",
      "workCount": 3
    },
    {
      "name": "うれまん/妄想族",
      "slug": "うれまん-妄想族",
      "workCount": 2
    },
    {
      "name": "エスワン ナンバーワンスタイル",
      "slug": "エスワン-ナンバーワンスタイル",
      "workCount": 471
    },
    {
      "name": "エムズビデオグループ",
      "slug": "エムズビデオグループ",
      "workCount": 17
    },
    {
      "name": "えむっ娘ラボ",
      "slug": "えむっ娘ラボ",
      "workCount": 13
    },
    {
      "name": "えろだるま/エマニエル",
      "slug": "えろだるま-エマニエル",
      "workCount": 10
    },
    {
      "name": "エンブレム",
      "slug": "エンブレム",
      "workCount": 1
    },
    {
      "name": "オーロラプロジェクト・アネックス",
      "slug": "オーロラプロジェクト・アネックス",
      "workCount": 22
    },
    {
      "name": "おかず研究所",
      "slug": "おかず研究所",
      "workCount": 5
    },
    {
      "name": "おっぱいゴールド",
      "slug": "おっぱいゴールド",
      "workCount": 1
    },
    {
      "name": "オフサイド",
      "slug": "オフサイド",
      "workCount": 1
    },
    {
      "name": "オフサイドトラップ",
      "slug": "オフサイドトラップ",
      "workCount": 3
    },
    {
      "name": "おペニペニワールドフェムボーイ/妄想族",
      "slug": "おペニペニワールドフェムボーイ-妄想族",
      "workCount": 1
    },
    {
      "name": "オリンポス",
      "slug": "オリンポス",
      "workCount": 14
    },
    {
      "name": "オルスタックソフト",
      "slug": "オルスタックソフト",
      "workCount": 15
    },
    {
      "name": "お夜食カンパニー",
      "slug": "お夜食カンパニー",
      "workCount": 3
    },
    {
      "name": "かぐや姫Pt/妄想族",
      "slug": "かぐや姫pt-妄想族",
      "workCount": 22
    },
    {
      "name": "カゲキっch",
      "slug": "カゲキっch",
      "workCount": 2
    },
    {
      "name": "かつお物産/妄想族",
      "slug": "かつお物産-妄想族",
      "workCount": 7
    },
    {
      "name": "カマタ映像",
      "slug": "カマタ映像",
      "workCount": 3
    },
    {
      "name": "カムカムぴゅっ！",
      "slug": "カムカムぴゅっ",
      "workCount": 4
    },
    {
      "name": "ぎがdeれいん",
      "slug": "ぎがdeれいん",
      "workCount": 4
    },
    {
      "name": "ぎがdeれいんMk-II/妄想族",
      "slug": "ぎがdeれいんmk-ii-妄想族",
      "workCount": 1
    },
    {
      "name": "キチックス/妄想族",
      "slug": "キチックス-妄想族",
      "workCount": 8
    },
    {
      "name": "きゃっち",
      "slug": "きゃっち",
      "workCount": 2
    },
    {
      "name": "ギャラリー",
      "slug": "ギャラリー",
      "workCount": 4
    },
    {
      "name": "グーニーズ",
      "slug": "グーニーズ",
      "workCount": 15
    },
    {
      "name": "グラフィティジャパン",
      "slug": "グラフィティジャパン",
      "workCount": 3
    },
    {
      "name": "クリスタル映像",
      "slug": "クリスタル映像",
      "workCount": 35
    },
    {
      "name": "クレイジーウォーカー",
      "slug": "クレイジーウォーカー",
      "workCount": 2
    },
    {
      "name": "グレイズ",
      "slug": "グレイズ",
      "workCount": 6
    },
    {
      "name": "グローバルメディアアネックス",
      "slug": "グローバルメディアアネックス",
      "workCount": 36
    },
    {
      "name": "グローバルメディアエンタテインメント",
      "slug": "グローバルメディアエンタテインメント",
      "workCount": 33
    },
    {
      "name": "グローリークエスト",
      "slug": "グローリークエスト",
      "workCount": 49
    },
    {
      "name": "ケイ・エム・プロデュース",
      "slug": "ケイ・エム・プロデュース",
      "workCount": 21
    },
    {
      "name": "ゲインコーポレーション",
      "slug": "ゲインコーポレーション",
      "workCount": 20
    },
    {
      "name": "ケー・トライブ",
      "slug": "ケー・トライブ",
      "workCount": 3
    },
    {
      "name": "ゲッツ！！ボンボン/妄想族",
      "slug": "ゲッツ-ボンボン-妄想族",
      "workCount": 23
    },
    {
      "name": "ゴーゴーズ",
      "slug": "ゴーゴーズ",
      "workCount": 13
    },
    {
      "name": "ゴーゴーズブラック/妄想族",
      "slug": "ゴーゴーズブラック-妄想族",
      "workCount": 1
    },
    {
      "name": "ゴールデンタイム",
      "slug": "ゴールデンタイム",
      "workCount": 2
    },
    {
      "name": "こぐま/妄想族",
      "slug": "こぐま-妄想族",
      "workCount": 1
    },
    {
      "name": "こすパコハメ撮りおじさん",
      "slug": "こすパコハメ撮りおじさん",
      "workCount": 4
    },
    {
      "name": "コスパ最強！！",
      "slug": "コスパ最強",
      "workCount": 1
    },
    {
      "name": "コスプレ坂69",
      "slug": "コスプレ坂69",
      "workCount": 1
    },
    {
      "name": "コスモス映像",
      "slug": "コスモス映像",
      "workCount": 9
    },
    {
      "name": "ゴリラのひまつぶし",
      "slug": "ゴリラのひまつぶし",
      "workCount": 1
    },
    {
      "name": "これぞ！素人",
      "slug": "これぞ-素人",
      "workCount": 1
    },
    {
      "name": "ザー汁王子/妄想族",
      "slug": "ザー汁王子-妄想族",
      "workCount": 6
    },
    {
      "name": "サディヴィレナウ！",
      "slug": "サディヴィレナウ",
      "workCount": 1
    },
    {
      "name": "サディスティックヴィレッジ",
      "slug": "サディスティックヴィレッジ",
      "workCount": 13
    },
    {
      "name": "ジェントルマン/妄想族",
      "slug": "ジェントルマン-妄想族",
      "workCount": 1
    },
    {
      "name": "シネマジック",
      "slug": "シネマジック",
      "workCount": 4
    },
    {
      "name": "シネマユニット・ガス",
      "slug": "シネマユニット・ガス",
      "workCount": 5
    },
    {
      "name": "ジミースキャンダル",
      "slug": "ジミースキャンダル",
      "workCount": 3
    },
    {
      "name": "シャイ企画",
      "slug": "シャイ企画",
      "workCount": 1
    },
    {
      "name": "ジュエル",
      "slug": "ジュエル",
      "workCount": 3
    },
    {
      "name": "しろうとがーる/妄想族",
      "slug": "しろうとがーる-妄想族",
      "workCount": 3
    },
    {
      "name": "シロウトネキ/妄想族",
      "slug": "シロウトネキ-妄想族",
      "workCount": 5
    },
    {
      "name": "しろうとヤッホー",
      "slug": "しろうとヤッホー",
      "workCount": 1
    },
    {
      "name": "スクープ",
      "slug": "スクープ",
      "workCount": 5
    },
    {
      "name": "スパークビジョン",
      "slug": "スパークビジョン",
      "workCount": 2
    },
    {
      "name": "スパイスビジュアル",
      "slug": "スパイスビジュアル",
      "workCount": 10
    },
    {
      "name": "スパルタン/妄想族",
      "slug": "スパルタン-妄想族",
      "workCount": 1
    },
    {
      "name": "スモークフィルムズ/妄想族",
      "slug": "スモークフィルムズ-妄想族",
      "workCount": 7
    },
    {
      "name": "セレブの友",
      "slug": "セレブの友",
      "workCount": 21
    },
    {
      "name": "センタービレッジ",
      "slug": "センタービレッジ",
      "workCount": 33
    },
    {
      "name": "タイト",
      "slug": "タイト",
      "workCount": 1
    },
    {
      "name": "ダイナマイトエンタープライズ",
      "slug": "ダイナマイトエンタープライズ",
      "workCount": 2
    },
    {
      "name": "タカラ映像",
      "slug": "タカラ映像",
      "workCount": 15
    },
    {
      "name": "ダスッ！",
      "slug": "ダスッ",
      "workCount": 86
    },
    {
      "name": "ダマちゃん。",
      "slug": "ダマちゃん",
      "workCount": 1
    },
    {
      "name": "たんぽぽ/妄想族",
      "slug": "たんぽぽ-妄想族",
      "workCount": 5
    },
    {
      "name": "チェリーズ",
      "slug": "チェリーズ",
      "workCount": 1
    },
    {
      "name": "チェリーズれぼ/妄想族",
      "slug": "チェリーズれぼ-妄想族",
      "workCount": 1
    },
    {
      "name": "チキチキカマー/妄想族",
      "slug": "チキチキカマー-妄想族",
      "workCount": 13
    },
    {
      "name": "ちゃんねる素人/妄想族",
      "slug": "ちゃんねる素人-妄想族",
      "workCount": 1
    },
    {
      "name": "チュンペイ",
      "slug": "チュンペイ",
      "workCount": 2
    },
    {
      "name": "ティーチャー/妄想族",
      "slug": "ティーチャー-妄想族",
      "workCount": 17
    },
    {
      "name": "ディープス",
      "slug": "ディープス",
      "workCount": 95
    },
    {
      "name": "ティッシュシコレール",
      "slug": "ティッシュシコレール",
      "workCount": 8
    },
    {
      "name": "ディレクターズ",
      "slug": "ディレクターズ",
      "workCount": 2
    },
    {
      "name": "デジタルアーク",
      "slug": "デジタルアーク",
      "workCount": 10
    },
    {
      "name": "テンダー",
      "slug": "テンダー",
      "workCount": 4
    },
    {
      "name": "トーキョー ヲタ連/妄想族",
      "slug": "トーキョー-ヲタ連-妄想族",
      "workCount": 2
    },
    {
      "name": "ドグマ",
      "slug": "ドグマ",
      "workCount": 13
    },
    {
      "name": "ドリームチケット",
      "slug": "ドリームチケット",
      "workCount": 14
    },
    {
      "name": "ながえスタイル",
      "slug": "ながえスタイル",
      "workCount": 22
    },
    {
      "name": "ナチュラルハイ",
      "slug": "ナチュラルハイ",
      "workCount": 51
    },
    {
      "name": "なでしこ",
      "slug": "なでしこ",
      "workCount": 1
    },
    {
      "name": "なまなま",
      "slug": "なまなま",
      "workCount": 25
    },
    {
      "name": "ネクスト",
      "slug": "ネクスト",
      "workCount": 10
    },
    {
      "name": "ノースキンズ",
      "slug": "ノースキンズ",
      "workCount": 3
    },
    {
      "name": "ノンフィクション",
      "slug": "ノンフィクション",
      "workCount": 1
    },
    {
      "name": "ハイカラ/妄想族",
      "slug": "ハイカラ-妄想族",
      "workCount": 9
    },
    {
      "name": "ハイライト",
      "slug": "ハイライト",
      "workCount": 2
    },
    {
      "name": "パコパコ団とゆかいな仲間たち/妄想族",
      "slug": "パコパコ団とゆかいな仲間たち-妄想族",
      "workCount": 22
    },
    {
      "name": "はじめ企画",
      "slug": "はじめ企画",
      "workCount": 10
    },
    {
      "name": "バビロン/妄想族",
      "slug": "バビロン-妄想族",
      "workCount": 5
    },
    {
      "name": "バミューダ/妄想族",
      "slug": "バミューダ-妄想族",
      "workCount": 2
    },
    {
      "name": "はめちゃん。",
      "slug": "はめちゃん",
      "workCount": 1
    },
    {
      "name": "はめちゃんGOLD/妄想族",
      "slug": "はめちゃんgold-妄想族",
      "workCount": 1
    },
    {
      "name": "ハラスメント",
      "slug": "ハラスメント",
      "workCount": 45
    },
    {
      "name": "パラダイステレビ",
      "slug": "パラダイステレビ",
      "workCount": 14
    },
    {
      "name": "バレマンッ！！/妄想族",
      "slug": "バレマンッ-妄想族",
      "workCount": 7
    },
    {
      "name": "パンじみデラックス",
      "slug": "パンじみデラックス",
      "workCount": 3
    },
    {
      "name": "ピーターズ",
      "slug": "ピーターズ",
      "workCount": 4
    },
    {
      "name": "ビッグモーカル",
      "slug": "ビッグモーカル",
      "workCount": 18
    },
    {
      "name": "ビビアン",
      "slug": "ビビアン",
      "workCount": 19
    },
    {
      "name": "ヒビノ",
      "slug": "ヒビノ",
      "workCount": 4
    },
    {
      "name": "ひよこ",
      "slug": "ひよこ",
      "workCount": 7
    },
    {
      "name": "フェチ眼",
      "slug": "フェチ眼",
      "workCount": 2
    },
    {
      "name": "フォーディメンション/エマニエル",
      "slug": "フォーディメンション-エマニエル",
      "workCount": 8
    },
    {
      "name": "プラネットプラス",
      "slug": "プラネットプラス",
      "workCount": 46
    },
    {
      "name": "ブラボー！",
      "slug": "ブラボー",
      "workCount": 3
    },
    {
      "name": "プラム",
      "slug": "プラム",
      "workCount": 31
    },
    {
      "name": "プリモ",
      "slug": "プリモ",
      "workCount": 22
    },
    {
      "name": "フレッシュ・ゴードン/妄想族",
      "slug": "フレッシュ・ゴードン-妄想族",
      "workCount": 2
    },
    {
      "name": "プレミアム",
      "slug": "プレミアム",
      "workCount": 47
    },
    {
      "name": "プレミアム熟女/エマニエル",
      "slug": "プレミアム熟女-エマニエル",
      "workCount": 8
    },
    {
      "name": "ブロッコリー/妄想族",
      "slug": "ブロッコリー-妄想族",
      "workCount": 23
    },
    {
      "name": "ふわとろ熟女/エマニエル",
      "slug": "ふわとろ熟女-エマニエル",
      "workCount": 3
    },
    {
      "name": "ペロネ",
      "slug": "ペロネ",
      "workCount": 15
    },
    {
      "name": "ホームルーム/妄想族",
      "slug": "ホームルーム-妄想族",
      "workCount": 7
    },
    {
      "name": "ホットエンターテイメント",
      "slug": "ホットエンターテイメント",
      "workCount": 27
    },
    {
      "name": "ボニータ/妄想族",
      "slug": "ボニータ-妄想族",
      "workCount": 16
    },
    {
      "name": "ポルチオ開発研究所",
      "slug": "ポルチオ開発研究所",
      "workCount": 1
    },
    {
      "name": "ま○こ銀行",
      "slug": "ま-こ銀行",
      "workCount": 5
    },
    {
      "name": "マーレーインターナショナル",
      "slug": "マーレーインターナショナル",
      "workCount": 3
    },
    {
      "name": "マキシング",
      "slug": "マキシング",
      "workCount": 6
    },
    {
      "name": "まぐろ物産",
      "slug": "まぐろ物産",
      "workCount": 1
    },
    {
      "name": "マザー",
      "slug": "マザー",
      "workCount": 9
    },
    {
      "name": "マックスエー",
      "slug": "マックスエー",
      "workCount": 26
    },
    {
      "name": "マドンナ",
      "slug": "マドンナ",
      "workCount": 296
    },
    {
      "name": "まるかあの/妄想族",
      "slug": "まるかあの-妄想族",
      "workCount": 3
    },
    {
      "name": "マンゴー将軍",
      "slug": "マンゴー将軍",
      "workCount": 1
    },
    {
      "name": "ミセスの素顔/エマニエル",
      "slug": "ミセスの素顔-エマニエル",
      "workCount": 6
    },
    {
      "name": "ミヤタ映像舎",
      "slug": "ミヤタ映像舎",
      "workCount": 1
    },
    {
      "name": "ミル",
      "slug": "ミル",
      "workCount": 3
    },
    {
      "name": "ムーディーズ",
      "slug": "ムーディーズ",
      "workCount": 453
    },
    {
      "name": "ムラっch",
      "slug": "ムラっch",
      "workCount": 3
    },
    {
      "name": "メガハーツ",
      "slug": "メガハーツ",
      "workCount": 1
    },
    {
      "name": "メタプリ",
      "slug": "メタプリ",
      "workCount": 1
    },
    {
      "name": "メディアブランド",
      "slug": "メディアブランド",
      "workCount": 2
    },
    {
      "name": "メモリーズ",
      "slug": "メモリーズ",
      "workCount": 2
    },
    {
      "name": "メロンぱんぱん/妄想族",
      "slug": "メロンぱんぱん-妄想族",
      "workCount": 1
    },
    {
      "name": "メンエス・オナクラ盗撮",
      "slug": "メンエス・オナクラ盗撮",
      "workCount": 12
    },
    {
      "name": "モグラ/妄想族",
      "slug": "モグラ-妄想族",
      "workCount": 1
    },
    {
      "name": "モッコ/妄想族",
      "slug": "モッコ-妄想族",
      "workCount": 11
    },
    {
      "name": "モデスト",
      "slug": "モデスト",
      "workCount": 6
    },
    {
      "name": "ゆず故障マシマシ/妄想族",
      "slug": "ゆず故障マシマシ-妄想族",
      "workCount": 3
    },
    {
      "name": "ラハイナ東海",
      "slug": "ラハイナ東海",
      "workCount": 1
    },
    {
      "name": "リコピン/妄想族",
      "slug": "リコピン-妄想族",
      "workCount": 3
    },
    {
      "name": "ルーブル",
      "slug": "ルーブル",
      "workCount": 6
    },
    {
      "name": "るさんちまん/妄想族",
      "slug": "るさんちまん-妄想族",
      "workCount": 2
    },
    {
      "name": "ルナティックス",
      "slug": "ルナティックス",
      "workCount": 39
    },
    {
      "name": "ルビー",
      "slug": "ルビー",
      "workCount": 25
    },
    {
      "name": "レアルワークス",
      "slug": "レアルワークス",
      "workCount": 32
    },
    {
      "name": "レイディックス",
      "slug": "レイディックス",
      "workCount": 4
    },
    {
      "name": "レズれ！",
      "slug": "レズれ",
      "workCount": 1
    },
    {
      "name": "ロイヤル",
      "slug": "ロイヤル",
      "workCount": 21
    },
    {
      "name": "ロータス",
      "slug": "ロータス",
      "workCount": 3
    },
    {
      "name": "ワー",
      "slug": "ワー",
      "workCount": 4
    },
    {
      "name": "ワープエンタテインメント",
      "slug": "ワープエンタテインメント",
      "workCount": 12
    },
    {
      "name": "ワンズファクトリー",
      "slug": "ワンズファクトリー",
      "workCount": 79
    },
    {
      "name": "ゑびすさん/妄想族",
      "slug": "ゑびすさん-妄想族",
      "workCount": 4
    },
    {
      "name": "ヲナサポベスト",
      "slug": "ヲナサポベスト",
      "workCount": 21
    },
    {
      "name": "闇録",
      "slug": "闇録",
      "workCount": 3
    },
    {
      "name": "一角獣",
      "slug": "一角獣",
      "workCount": 5
    },
    {
      "name": "宇宙企画",
      "slug": "宇宙企画",
      "workCount": 5
    },
    {
      "name": "俺の素人-Z- SECOND IMPACT",
      "slug": "俺の素人-z-second-impact",
      "workCount": 16
    },
    {
      "name": "下半身タイガース/妄想族",
      "slug": "下半身タイガース-妄想族",
      "workCount": 14
    },
    {
      "name": "花と蜜",
      "slug": "花と蜜",
      "workCount": 5
    },
    {
      "name": "海外専門.com",
      "slug": "海外専門-com",
      "workCount": 2
    },
    {
      "name": "姦乱者/妄想族",
      "slug": "姦乱者-妄想族",
      "workCount": 5
    },
    {
      "name": "君を食べたい/妄想族",
      "slug": "君を食べたい-妄想族",
      "workCount": 1
    },
    {
      "name": "堅者の食卓/妄想族",
      "slug": "堅者の食卓-妄想族",
      "workCount": 1
    },
    {
      "name": "犬/妄想族",
      "slug": "犬-妄想族",
      "workCount": 5
    },
    {
      "name": "五次元",
      "slug": "五次元",
      "workCount": 3
    },
    {
      "name": "五十路ん",
      "slug": "五十路ん",
      "workCount": 3
    },
    {
      "name": "光夜蝶",
      "slug": "光夜蝶",
      "workCount": 2
    },
    {
      "name": "三和出版",
      "slug": "三和出版",
      "workCount": 7
    },
    {
      "name": "山と空/妄想族",
      "slug": "山と空-妄想族",
      "workCount": 30
    },
    {
      "name": "熟撮/妄想族",
      "slug": "熟撮-妄想族",
      "workCount": 4
    },
    {
      "name": "熟女JAPAN",
      "slug": "熟女japan",
      "workCount": 14
    },
    {
      "name": "熟女LABO",
      "slug": "熟女labo",
      "workCount": 2
    },
    {
      "name": "熟女プライベート/熟女卍",
      "slug": "熟女プライベート-熟女卍",
      "workCount": 1
    },
    {
      "name": "熟女塾/エマニエル",
      "slug": "熟女塾-エマニエル",
      "workCount": 5
    },
    {
      "name": "熟女大学/熟女卍",
      "slug": "熟女大学-熟女卍",
      "workCount": 2
    },
    {
      "name": "熟女本舗/エマニエル",
      "slug": "熟女本舗-エマニエル",
      "workCount": 1
    },
    {
      "name": "熟中/エマニエル",
      "slug": "熟中-エマニエル",
      "workCount": 2
    },
    {
      "name": "信長/エマニエル",
      "slug": "信長-エマニエル",
      "workCount": 1
    },
    {
      "name": "新セカイ/妄想族",
      "slug": "新セカイ-妄想族",
      "workCount": 4
    },
    {
      "name": "親父の個撮",
      "slug": "親父の個撮",
      "workCount": 12
    },
    {
      "name": "人妻援護会/エマニエル",
      "slug": "人妻援護会-エマニエル",
      "workCount": 7
    },
    {
      "name": "人妻花園劇場",
      "slug": "人妻花園劇場",
      "workCount": 3
    },
    {
      "name": "推しムス",
      "slug": "推しムス",
      "workCount": 2
    },
    {
      "name": "西新宿マッサージ本舗",
      "slug": "西新宿マッサージ本舗",
      "workCount": 1
    },
    {
      "name": "赤面女子",
      "slug": "赤面女子",
      "workCount": 28
    },
    {
      "name": "切り売りのおかず屋さん",
      "slug": "切り売りのおかず屋さん",
      "workCount": 34
    },
    {
      "name": "全日本カメコ協同組合/妄想族",
      "slug": "全日本カメコ協同組合-妄想族",
      "workCount": 10
    },
    {
      "name": "素人39",
      "slug": "素人39",
      "workCount": 8
    },
    {
      "name": "素人CLOVER",
      "slug": "素人clover",
      "workCount": 3
    },
    {
      "name": "素人Pro",
      "slug": "素人pro",
      "workCount": 3
    },
    {
      "name": "素人ホイホイ/妄想族",
      "slug": "素人ホイホイ-妄想族",
      "workCount": 23
    },
    {
      "name": "素人まっちんぐEX/妄想族",
      "slug": "素人まっちんぐex-妄想族",
      "workCount": 1
    },
    {
      "name": "素人喫茶/妄想族",
      "slug": "素人喫茶-妄想族",
      "workCount": 3
    },
    {
      "name": "綜実社/妄想族",
      "slug": "綜実社-妄想族",
      "workCount": 1
    },
    {
      "name": "即ヌキ",
      "slug": "即ヌキ",
      "workCount": 86
    },
    {
      "name": "即ハメちゃん",
      "slug": "即ハメちゃん",
      "workCount": 1
    },
    {
      "name": "唾鬼",
      "slug": "唾鬼",
      "workCount": 2
    },
    {
      "name": "脱ぐのは恥だがペニス立つ/妄想族",
      "slug": "脱ぐのは恥だがペニス立つ-妄想族",
      "workCount": 18
    },
    {
      "name": "痴女ヘブン",
      "slug": "痴女ヘブン",
      "workCount": 25
    },
    {
      "name": "竹書房",
      "slug": "竹書房",
      "workCount": 2
    },
    {
      "name": "中嶋興業",
      "slug": "中嶋興業",
      "workCount": 1
    },
    {
      "name": "中目黒人妻メンズエステ",
      "slug": "中目黒人妻メンズエステ",
      "workCount": 4
    },
    {
      "name": "椿鳳院",
      "slug": "椿鳳院",
      "workCount": 2
    },
    {
      "name": "泥棒猫/エマニエル",
      "slug": "泥棒猫-エマニエル",
      "workCount": 5
    },
    {
      "name": "電脳ラスプーチン",
      "slug": "電脳ラスプーチン",
      "workCount": 13
    },
    {
      "name": "投稿FANクラブ",
      "slug": "投稿fanクラブ",
      "workCount": 3
    },
    {
      "name": "東京恋人",
      "slug": "東京恋人",
      "workCount": 1
    },
    {
      "name": "桃太郎映像出版",
      "slug": "桃太郎映像出版",
      "workCount": 171
    },
    {
      "name": "同人AV倶楽部/妄想族",
      "slug": "同人av倶楽部-妄想族",
      "workCount": 12
    },
    {
      "name": "毒宴会",
      "slug": "毒宴会",
      "workCount": 4
    },
    {
      "name": "独占素人",
      "slug": "独占素人",
      "workCount": 9
    },
    {
      "name": "凸凹はぁと",
      "slug": "凸凹はぁと",
      "workCount": 2
    },
    {
      "name": "肉厚食堂/妄想族",
      "slug": "肉厚食堂-妄想族",
      "workCount": 1
    },
    {
      "name": "日本橋映像EX/エマニエル",
      "slug": "日本橋映像ex-エマニエル",
      "workCount": 1
    },
    {
      "name": "濡壺/妄想族",
      "slug": "濡壺-妄想族",
      "workCount": 1
    },
    {
      "name": "美人魔女/エマニエル",
      "slug": "美人魔女-エマニエル",
      "workCount": 2
    },
    {
      "name": "変態紳士倶楽部",
      "slug": "変態紳士倶楽部",
      "workCount": 29
    },
    {
      "name": "豊彦",
      "slug": "豊彦",
      "workCount": 13
    },
    {
      "name": "僕たち男の娘",
      "slug": "僕たち男の娘",
      "workCount": 3
    },
    {
      "name": "本中",
      "slug": "本中",
      "workCount": 42
    },
    {
      "name": "未満",
      "slug": "未満",
      "workCount": 4
    },
    {
      "name": "未来OKAZUラボ",
      "slug": "未来okazuラボ",
      "workCount": 1
    },
    {
      "name": "無垢",
      "slug": "無垢",
      "workCount": 33
    },
    {
      "name": "無理くりえいてぃぶ",
      "slug": "無理くりえいてぃぶ",
      "workCount": 10
    },
    {
      "name": "名作ポルノ",
      "slug": "名作ポルノ",
      "workCount": 4
    },
    {
      "name": "木曜だヨ！全員集合っ！！",
      "slug": "木曜だヨ-全員集合っ",
      "workCount": 12
    },
    {
      "name": "有閑ミセス/エマニエル",
      "slug": "有閑ミセス-エマニエル",
      "workCount": 7
    },
    {
      "name": "夕焼けジェラシー",
      "slug": "夕焼けジェラシー",
      "workCount": 10
    },
    {
      "name": "穢土-EDO-",
      "slug": "穢土-edo",
      "workCount": 5
    },
    {
      "name": "蜃気楼",
      "slug": "蜃気楼",
      "workCount": 2
    }
  ]
}
